pyHMT2D/__about__.py
pyHMT2D/__common__.py
pyHMT2D/__init__.py
pyHMT2D/Calibration/Calibrator.py
pyHMT2D/Calibration/Measurements.py
pyHMT2D/Calibration/Objectives.py
pyHMT2D/Calibration/Optimizer.py
pyHMT2D/Calibration/Parameters.py
pyHMT2D/Calibration/__init__.py
pyHMT2D/Hydraulic_Models_Data/__init__.py
pyHMT2D/Hydraulic_Models_Data/Backwater_1D/Backwater_1D_Data.py
pyHMT2D/Hydraulic_Models_Data/Backwater_1D/Backwater_1D_Model.py
pyHMT2D/Hydraulic_Models_Data/Backwater_1D/__init__.py
pyHMT2D/Hydraulic_Models_Data/Hydraulic_Models_Data_Base/HydraulicData.py
pyHMT2D/Hydraulic_Models_Data/Hydraulic_Models_Data_Base/HydraulicModel.py
pyHMT2D/Hydraulic_Models_Data/Hydraulic_Models_Data_Base/__init__.py
pyHMT2D/Hydraulic_Models_Data/RAS_2D/HEC_RAS_Model.py
pyHMT2D/Hydraulic_Models_Data/RAS_2D/RAS_2D_Data.py
pyHMT2D/Hydraulic_Models_Data/RAS_2D/__init__.py
pyHMT2D/Hydraulic_Models_Data/RAS_2D/helpers.py
pyHMT2D/Hydraulic_Models_Data/SRH_2D/SRH_2D_Data.py
pyHMT2D/Hydraulic_Models_Data/SRH_2D/SRH_2D_Model.py
pyHMT2D/Hydraulic_Models_Data/SRH_2D/__init__.py
pyHMT2D/Hydraulic_Models_Data/SRH_2D/helpers.py
pyHMT2D/Misc/RAS_to_SRH_Converter.py
pyHMT2D/Misc/Terrain.py
pyHMT2D/Misc/__init__.py
pyHMT2D/Misc/gmsh2d_to_srh.py
pyHMT2D/Misc/tools.py
pyHMT2D/Misc/vtk_utilities.py
pyHMT2D/Parametric_Study/Parametric_Study.py
pyHMT2D/Parametric_Study/Sampler.py
pyHMT2D/Parametric_Study/__init__.py
pyHMT2D/cli/__init__.py
pyHMT2D/cli/hmt_calibrate.py
pyHMT2D/cli/ras_to_srh.py
pyHMT2D/cli/srh_mesh_to_vtk.py
pyHMT2D/cli/srh_to_vtk.py
pyHMT2D-1.0.6.dist-info/LICENSE
pyHMT2D-1.0.6.dist-info/METADATA
pyHMT2D-1.0.6.dist-info/WHEEL
pyHMT2D-1.0.6.dist-info/entry_points.txt
pyHMT2D-1.0.6.dist-info/top_level.txt
pyHMT2D-1.0.6.dist-info/RECORD
