Metadata-Version: 2.1
Name: pyHMT2D
Version: 1.0.6
Summary: Two-dimensional hydraulic modeling tools in Python
Home-page: https://github.com/psu-efd/pyHMT2D
Author: Xiaofeng Liu
Author-email: xiaofengliu19@gmail.com
License: MIT
Platform: UNKNOWN
Classifier: Development Status :: 4 - Beta
Classifier: Intended Audience :: Science/Research
Classifier: License :: OSI Approved :: MIT License
Classifier: Programming Language :: Python
Classifier: Programming Language :: Python :: 3
Classifier: Programming Language :: Python :: 3.7
Classifier: Programming Language :: Python :: 3.8
Classifier: Programming Language :: Python :: Implementation :: CPython
Classifier: Programming Language :: Python :: Implementation :: PyPy
Classifier: Topic :: Scientific/Engineering
Classifier: Topic :: Utilities
Requires-Python: >=3.7.0, <3.9.9
License-File: LICENSE
Requires-Dist: numpy
Requires-Dist: vtk (>=9.0.2)
Requires-Dist: h5py
Requires-Dist: scipy
Requires-Dist: affine
Requires-Dist: meshio
Requires-Dist: scikit-optimize
Provides-Extra: georeferencing
Requires-Dist: osgeo ; extra == 'georeferencing'
Provides-Extra: hec-ras_control
Requires-Dist: pywin32 ; extra == 'hec-ras_control'
